remarkable_cli/__init__.py
remarkable_cli/__main__.py
remarkable_cli/client.py
remarkable_cli/convert_rm.py
remarkable_cli/pens/__init__.py
remarkable_cli/pens/pen.py
tests/__init__.py
tests/test_convert_rm.py
remarkable_cli-0.3.2.dist-info/LICENSE
remarkable_cli-0.3.2.dist-info/METADATA
remarkable_cli-0.3.2.dist-info/WHEEL
remarkable_cli-0.3.2.dist-info/entry_points.txt
remarkable_cli-0.3.2.dist-info/top_level.txt
remarkable_cli-0.3.2.dist-info/RECORD
