Metadata-Version: 2.1
Name: remarkable-cli
Version: 0.3.2
Summary: An unofficial CLI for interacting with the Remarkable tablet.
Home-page: https://github.com/awwong1/remarkable-cli
Author: Alexander Wong
Author-email: alex@udia.ca
License: Apache-2.0
Platform: UNKNOWN
Classifier: License :: OSI Approved :: Apache Software License
Classifier: Environment :: Console
Classifier: Natural Language :: English
Classifier: Operating System :: POSIX :: Linux
Classifier: Topic :: Utilities
Classifier: Programming Language :: Python :: 3
Classifier: Programming Language :: Python :: 3 :: Only
Requires-Dist: paramiko
Requires-Dist: requests
Requires-Dist: svglib
Requires-Dist: reportlab
